credentials/__init__.py
credentials/admin.py
credentials/api_views.py
credentials/apps.py
credentials/classes.py
credentials/credential_backends.py
credentials/events.py
credentials/forms.py
credentials/icons.py
credentials/links.py
credentials/models.py
credentials/permissions.py
credentials/serializers.py
credentials/urls.py
credentials/views.py
credentials/migrations/0001_initial.py
credentials/migrations/0002_auto_20201215_0523.py
credentials/migrations/0003_auto_20210207_0823.py
credentials/migrations/0004_auto_20210207_0823.py
credentials/migrations/0005_auto_20210207_0840.py
credentials/migrations/__init__.py
credentials/tests/__init__.py
credentials/tests/literals.py
credentials/tests/mixins.py
credentials/tests/test_api.py
credentials/tests/test_views.py
mayan_credentials-1.4.1.dist-info/LICENSE
mayan_credentials-1.4.1.dist-info/METADATA
mayan_credentials-1.4.1.dist-info/WHEEL
mayan_credentials-1.4.1.dist-info/top_level.txt
mayan_credentials-1.4.1.dist-info/RECORD
