Metadata-Version: 2.1
Name: mayan-credentials
Version: 1.4.1
Summary: Credentials
Home-page: https://gitlab.com/mayan-edms/credentials
Author: Roberto Rosario
Author-email: roberto.rosario@mayan-edms.com
License: Apache 2.0
Platform: any
Classifier: Development Status :: 5 - Production/Stable
Classifier: Environment :: Web Environment
Classifier: Framework :: Django
Classifier: Intended Audience :: Education
Classifier: Intended Audience :: End Users/Desktop
Classifier: Intended Audience :: Developers
Classifier: Intended Audience :: Information Technology
Classifier: License :: OSI Approved :: Apache Software License
Classifier: Natural Language :: English
Classifier: Operating System :: POSIX
Classifier: Programming Language :: Python
Classifier: Programming Language :: Python :: 3
Classifier: Programming Language :: Python :: 3.5
Classifier: Programming Language :: Python :: 3.6
Classifier: Programming Language :: Python :: 3.7
Classifier: Programming Language :: Python :: 3.8
Classifier: Topic :: Internet :: WWW/HTTP
Classifier: Topic :: Internet :: WWW/HTTP :: WSGI :: Application
Classifier: Topic :: Communications :: File Sharing
Requires-Python: !=3.0.*, !=3.1.*, !=3.2.*, !=3.3.*
License-File: LICENSE
